[
  {
    "id": 31,
    "geoId": "ID-JK",
    "name": "DKI JAKARTA",
    "member_id": 384,
    "total": 1274
  },
  {
    "id": 32,
    "geoId": "ID-JB",
    "name": "JAWA BARAT",
    "member_id": 735,
    "total": 265
  },
  {
    "id": 35,
    "geoId": "ID-JI",
    "name": "JAWA TIMUR",
    "member_id": 1003,
    "total": 203
  },
  {
    "id": 33,
    "geoId": "ID-JT",
    "name": "JAWA TENGAH",
    "member_id": 822,
    "total": 124
  },
  {
    "id": 36,
    "geoId": "ID-BT",
    "name": "BANTEN",
    "member_id": 620,
    "total": 109
  },
  {
    "id": 34,
    "geoId": "ID-YO",
    "name": "DI YOGYAKARTA",
    "member_id": 799,
    "total": 78
  },
  {
    "id": 12,
    "geoId": "ID-SU",
    "name": "SUMATERA UTARA",
    "member_id": 1404,
    "total": 51
  },
  {
    "id": 21,
    "geoId": "ID-KR",
    "name": "KEPULAUAN RIAU",
    "member_id": 623,
    "total": 40
  },
  {
    "id": 51,
    "geoId": "ID-BA",
    "name": "BALI",
    "member_id": 412,
    "total": 37
  },
  {
    "id": 73,
    "geoId": "ID-SN",
    "name": "SULAWESI SELATAN",
    "member_id": 709,
    "total": 36
  },
  {
    "id": 18,
    "geoId": "ID-LA",
    "name": "LAMPUNG",
    "member_id": 961,
    "total": 31
  },
  {
    "id": 14,
    "geoId": "ID-RI",
    "name": "RIAU",
    "member_id": 513,
    "total": 31
  },
  {
    "id": 16,
    "geoId": "ID-SS",
    "name": "SUMATERA SELATAN",
    "member_id": 446,
    "total": 28
  },
  {
    "id": 64,
    "geoId": "ID-KI",
    "name": "KALIMANTAN TIMUR",
    "member_id": 479,
    "total": 23
  },
  {
    "id": 13,
    "geoId": "ID-SB",
    "name": "SUMATERA BARAT",
    "member_id": 661,
    "total": 22
  },
  {
    "id": 61,
    "geoId": "ID-KB",
    "name": "KALIMANTAN BARAT",
    "member_id": 594,
    "total": 13
  },
  {
    "id": 71,
    "geoId": "ID-SA",
    "name": "SULAWESI UTARA",
    "member_id": 2065,
    "total": 13
  },
  {
    "id": 63,
    "geoId": "ID-KS",
    "name": "KALIMANTAN SELATAN",
    "member_id": 525,
    "total": 12
  },
  {
    "id": 15,
    "geoId": "ID-JA",
    "name": "JAMBI",
    "member_id": 776,
    "total": 11
  },
  {
    "id": 11,
    "geoId": "ID-AC",
    "name": "ACEH",
    "member_id": 1272,
    "total": 11
  },
  {
    "id": 52,
    "geoId": "ID-NB",
    "name": "NUSA TENGGARA BARAT",
    "member_id": 1720,
    "total": 10
  },
  {
    "id": 75,
    "geoId": "ID-GO",
    "name": "GORONTALO",
    "member_id": 684,
    "total": 10
  },
  {
    "id": 72,
    "geoId": "ID-ST",
    "name": "SULAWESI TENGAH",
    "member_id": 743,
    "total": 8
  },
  {
    "id": 94,
    "geoId": "ID-PA",
    "name": "PAPUA",
    "member_id": 1799,
    "total": 7
  },
  {
    "id": 62,
    "geoId": "ID-KT",
    "name": "KALIMANTAN TENGAH",
    "member_id": 789,
    "total": 5
  },
  {
    "id": 74,
    "geoId": "ID-SG",
    "name": "SULAWESI TENGGARA",
    "member_id": 904,
    "total": 5
  },
  {
    "id": 53,
    "geoId": "ID-NT",
    "name": "NUSA TENGGARA TIMUR",
    "member_id": 647,
    "total": 4
  },
  {
    "id": 19,
    "geoId": "ID-BB",
    "name": "KEPULAUAN BANGKA BELITUNG",
    "member_id": 954,
    "total": 4
  },
  {
    "id": 91,
    "geoId": "ID-PB",
    "name": "PAPUA BARAT",
    "member_id": 1981,
    "total": 3
  },
  {
    "id": 81,
    "geoId": "ID-MA",
    "name": "MALUKU",
    "member_id": 908,
    "total": 2
  },
  {
    "id": 82,
    "geoId": "ID-MU",
    "name": "MALUKU UTARA",
    "member_id": 2478,
    "total": 2
  },
  {
    "id": 65,
    "geoId": "ID-KU",
    "name": "KALIMANTAN UTARA",
    "member_id": 2926,
    "total": 1
  },
  {
    "id": 17,
    "geoId": "ID-BE",
    "name": "BENGKULU",
    "member_id": "NULL",
    "total": 0
  },
  {
    "id": 76,
    "geoId": "ID-SR",
    "name": "SULAWESI BARAT",
    "member_id": 2788,
    "total": 1
  }
]
